src/__init__.py
src/main.py
math_command_line-0.0.1.dist-info/LICENSE
math_command_line-0.0.1.dist-info/METADATA
math_command_line-0.0.1.dist-info/WHEEL
math_command_line-0.0.1.dist-info/entry_points.txt
math_command_line-0.0.1.dist-info/top_level.txt
math_command_line-0.0.1.dist-info/RECORD
