Metadata-Version: 2.1
Name: math-command-line
Version: 0.0.1
Summary: A command line tool to evaluate mathematical expressions
Home-page: https://github.com/Parsa2820/math
Author: Parsa Mohammadian
Author-email: parsa2820@gmail.com
License: MIT
Requires-Python: >=3.0
License-File: LICENSE
